README.md
setup.py
ardana_packager/__init__.py
ardana_packager/activate.py
ardana_packager/ansible.py
ardana_packager/cache.py
ardana_packager/cmd.py
ardana_packager/config.py
ardana_packager/error.py
ardana_packager/expand.py
ardana_packager/indexer.py
ardana_packager/service.py
ardana_packager/setup_systemd.py
ardana_packager/symlinks.py
ardana_packager/venv_edit.py
ardana_packager/version.py
ardana_packager/versions.yml
ardana_packager.egg-info/PKG-INFO
ardana_packager.egg-info/SOURCES.txt
ardana_packager.egg-info/dependency_links.txt
ardana_packager.egg-info/entry_points.txt
ardana_packager.egg-info/requires.txt
ardana_packager.egg-info/top_level.txt