Metadata-Version: 1.1
Name: ardana-packager
Version: 0.0.3
Summary: Prepackaged virtualenv deployment tool
Home-page: UNKNOWN
Author: Hewlett-Packard Development Company, L.P.
Author-email: UNKNOWN
License: UNKNOWN
Platform: UNKNOWN
Classifier: Development Status :: 3 - Alpha
Classifier: Topic :: Utilities
Classifier: License :: OSI Approved :: Apache Software License
Classifier: Operating System :: POSIX :: Linux
Classifier: Programming Language :: Python
Classifier: Programming Language :: Python :: 2
Classifier: Programming Language :: Python :: 2.7
Classifier: Programming Language :: Python :: 2.6
